jinjafx_server/__init__.py
jinjafx_server/__main__.py
jinjafx_server/jinjafx_server.py
jinjafx_server/pandoc/reference.docx
jinjafx_server/www/dt.html
jinjafx_server/www/index.html
jinjafx_server/www/jinjafx.css
jinjafx_server/www/jinjafx.png
jinjafx_server/www/jinjafx_dt.css
jinjafx_server/www/jinjafx_dt.js
jinjafx_server/www/jinjafx_logs.css
jinjafx_server/www/jinjafx_logs.js
jinjafx_server/www/jinjafx_m.css
jinjafx_server/www/jinjafx_m.js
jinjafx_server/www/jinjafx_o.css
jinjafx_server/www/jinjafx_o.js
jinjafx_server/www/logs.html
jinjafx_server/www/output.html
jinjafx_server-26.2.0.dist-info/licenses/LICENSE
jinjafx_server-26.2.0.dist-info/METADATA
jinjafx_server-26.2.0.dist-info/WHEEL
jinjafx_server-26.2.0.dist-info/entry_points.txt
jinjafx_server-26.2.0.dist-info/top_level.txt
jinjafx_server-26.2.0.dist-info/RECORD
