Metadata-Version: 2.4
Name: jinjafx_server
Version: 26.2.0
Summary: JinjaFx Server - Jinja2 Templating Tool
Author-email: Chris Mason <chris@netnix.org>
License-Expression: MIT
Project-URL: Repository, https://github.com/cmason3/jinjafx_server.git
Project-URL: Issues, https://github.com/cmason3/jinjafx_server/issues
Project-URL: Changelog, https://github.com/cmason3/jinjafx_server/blob/main/CHANGELOG.md
Classifier: Development Status :: 5 - Production/Stable
Classifier: Programming Language :: Python :: 3
Requires-Python: >=3.10
License-File: LICENSE
Requires-Dist: jinjafx>=1.27.1
Requires-Dist: requests
Requires-Dist: cmarkgfm>=0.5.0
Requires-Dist: emoji
Dynamic: license-file
